NetHyTech_Pyttsx3_Speak/__init__.py
NetHyTech_Pyttsx3_Speak-1.0.dist-info/METADATA
NetHyTech_Pyttsx3_Speak-1.0.dist-info/WHEEL
NetHyTech_Pyttsx3_Speak-1.0.dist-info/top_level.txt
NetHyTech_Pyttsx3_Speak-1.0.dist-info/RECORD
