Metadata-Version: 2.1
Name: NetHyTech-Pyttsx3-Speak
Version: 1.0
Summary: A package for controlling mouse actions using hand gestures
Home-page: https://github.com/AnubhavChaturvedi-GitHub/NetHyTech-MCV
Author: Anubhav Chaturvedi
Author-email: chaturvedianubhav520@gmail.com
Classifier: Programming Language :: Python :: 3
Classifier: License :: OSI Approved :: MIT License
Classifier: Operating System :: OS Independent
Requires-Python: >=3.6
Requires-Dist: pyttsx3
Requires-Dist: textblob
